bingx_headers_generator/__init__.py
bingx_headers_generator/__version__.py
bingx_headers_generator/generator.py
bingx_headers_generator-1.0.4.dist-info/METADATA
bingx_headers_generator-1.0.4.dist-info/WHEEL
bingx_headers_generator-1.0.4.dist-info/top_level.txt
bingx_headers_generator-1.0.4.dist-info/RECORD
